zscaner/__init__.py
zscaner-1.3.0.dist-info/METADATA
zscaner-1.3.0.dist-info/WHEEL
zscaner-1.3.0.dist-info/top_level.txt
zscaner-1.3.0.dist-info/RECORD
