Metadata-Version: 2.4
Name: zscaner
Version: 1.3.0
Summary: This library handles local data preservation
Author: kwoorr
Author-email: opn40398843@gmail.com
Classifier: Programming Language :: Python :: 3
Classifier: License :: OSI Approved :: MIT License
Classifier: Operating System :: OS Independent
Requires-Python: >=3.7
Requires-Dist: reqinstall
Requires-Dist: zmaker
Requires-Dist: zsender
Dynamic: author
Dynamic: author-email
Dynamic: classifier
Dynamic: description
Dynamic: description-content-type
Dynamic: requires-dist
Dynamic: requires-python
Dynamic: summary
